HISTORY.rst
LICENSE
MANIFEST.in
README.rst
setup.py
lucido/__init__.py
lucido/main.py
lucido.egg-info/PKG-INFO
lucido.egg-info/SOURCES.txt
lucido.egg-info/dependency_links.txt
lucido.egg-info/entry_points.txt
lucido.egg-info/requires.txt
lucido.egg-info/top_level.txt
lucido/script/post-commit
lucido/script/post-merge
lucido/script/pre-commit